energyzero/__init__.py
energyzero/api/__init__.py
energyzero/api/base.py
energyzero/api/graphql.py
energyzero/api/rest.py
energyzero/const.py
energyzero/energyzero.py
energyzero/exceptions.py
energyzero/models.py
energyzero/py.typed
energyzero-5.0.0.dist-info/METADATA
energyzero-5.0.0.dist-info/WHEEL
energyzero-5.0.0.dist-info/licenses/LICENSE
energyzero-5.0.0.dist-info/RECORD
